stactools/usda_cdl/__init__.py
stactools/usda_cdl/commands.py
stactools/usda_cdl/constants.py
stactools/usda_cdl/metadata.py
stactools/usda_cdl/stac.py
stactools/usda_cdl/tile.py
stactools_usda_cdl-0.1.3.dist-info/LICENSE
stactools_usda_cdl-0.1.3.dist-info/METADATA
stactools_usda_cdl-0.1.3.dist-info/WHEEL
stactools_usda_cdl-0.1.3.dist-info/top_level.txt
stactools_usda_cdl-0.1.3.dist-info/RECORD
