Metadata-Version: 2.1
Name: stactools-usda-cdl
Version: 0.1.3
Summary: stactools package for USDA Cropland Data Layer
Home-page: https://github.com/stactools-packages/usda-cdl
Author: Paola Holleway
Author-email: paolaholleway@gmail.com
Project-URL: Issues, https://github.com/stactools-packages/usda-cdl/issues
Keywords: stactools,pystac,catalog,STAC
Classifier: Development Status :: 4 - Beta
Classifier: License :: OSI Approved :: Apache Software License
Classifier: Programming Language :: Python :: 3.8
Classifier: Programming Language :: Python :: 3.9
Classifier: Programming Language :: Python :: 3.10
Classifier: Programming Language :: Python :: 3.11
License-File: LICENSE
Requires-Dist: click (>=8.1.3)
Requires-Dist: pystac (>=1.6.1)
Requires-Dist: requests (>=2.28.1)
Requires-Dist: stactools (>=0.4.3)
Requires-Dist: tqdm (>=4.64.1)
